TGLightWindow.kpf
setup.py
TGLightWindow/__init__.py
TGLightWindow/release.py
TGLightWindow/widgets.py
TGLightWindow.egg-info/PKG-INFO
TGLightWindow.egg-info/SOURCES.txt
TGLightWindow.egg-info/dependency_links.txt
TGLightWindow.egg-info/entry_points.txt
TGLightWindow.egg-info/not-zip-safe
TGLightWindow.egg-info/paster_plugins.txt
TGLightWindow.egg-info/requires.txt
TGLightWindow.egg-info/sqlobject.txt
TGLightWindow.egg-info/top_level.txt
TGLightWindow/static/css/default.css
TGLightWindow/static/css/lightwindow.css
TGLightWindow/static/images/ajax-loading.gif
TGLightWindow/static/images/arrow-down.gif
TGLightWindow/static/images/arrow-up.gif
TGLightWindow/static/images/black-70.png
TGLightWindow/static/images/black.png
TGLightWindow/static/images/blank.gif
TGLightWindow/static/images/nextlabel.gif
TGLightWindow/static/images/pattern_148-70.png
TGLightWindow/static/images/pattern_148.gif
TGLightWindow/static/images/prevlabel.gif
TGLightWindow/static/javascript/lightwindow.js
TGLightWindow/templates/__init__.py
