Metadata-Version: 1.0
Name: TGLightWindow
Version: 2.0
Summary: LightWindow JS packaged as TurboGears widget
Home-page: http://tgwidgets.ossdl.de/
Author: W-Mark Kubacki
Author-email: wmark.tglightwindow@hurrikane.de
License: MIT
Download-URL: http://static.ossdl.de/tgwidgets/downloads/
Keywords: turbogears.widgets
Platform: UNKNOWN
Classifier: Development Status :: 5 - Production/Stable
Classifier: Operating System :: OS Independent
Classifier: Programming Language :: Python
Classifier: Programming Language :: JavaScript
Classifier: Topic :: Software Development :: Libraries :: Python Modules
Classifier: Framework :: TurboGears
Classifier: Framework :: TurboGears :: Widgets
Classifier: License :: OSI Approved :: MIT License
